checkout.py
setup.cfg
setup.py
taskcluster_checkout.egg-info/PKG-INFO
taskcluster_checkout.egg-info/SOURCES.txt
taskcluster_checkout.egg-info/dependency_links.txt
taskcluster_checkout.egg-info/entry_points.txt
taskcluster_checkout.egg-info/pbr.json
taskcluster_checkout.egg-info/requires.txt
taskcluster_checkout.egg-info/top_level.txt