Metadata-Version: 1.1
Name: taskcluster-checkout
Version: 0.1.0
Summary: Checkout cached repositories served by TaskCluster
Home-page: https://github.com/acmiyaguchi/taskcluster-checkout.git
Author: Anthony Miyaguchi
Author-email: amiyaguchi@mozilla.com
License: MPL2
Download-URL: https://github.com/acmiyaguchi/taskcluster-checkout/tarball/0.1.0
Platform: UNKNOWN
